memcache_wrapper/__init__.py
memcache_wrapper/memcache_wrapper.py
memcache_wrapper-1.0.4.dist-info/DESCRIPTION.rst
memcache_wrapper-1.0.4.dist-info/METADATA
memcache_wrapper-1.0.4.dist-info/RECORD
memcache_wrapper-1.0.4.dist-info/WHEEL
memcache_wrapper-1.0.4.dist-info/metadata.json
memcache_wrapper-1.0.4.dist-info/top_level.txt
