Metadata-Version: 2.0
Name: memcache-wrapper
Version: 1.0.4
Summary: A Python function wrapper to cache method results using memcache
Home-page: https://github.com/azraelxyz/memcache_wrapper
Author: xwhuang
Author-email: xwhuang@qnap.com
License: UNKNOWN
Platform: UNKNOWN
Classifier: Topic :: Utilities
Requires-Dist: mockcache
Requires-Dist: mockito
Requires-Dist: python-memcached
